{
  "id": "766",
  "code": "val-7",
  "name": "VAL 7",
  "type": "wreck",
  "lat": "52.3710586",
  "lon": "5.0090060",
  "location": "Buiten Ij, Nederland",
  "firstdate": null,
  "firstyear": "1590",
  "firstyearend": null,
  "lastdate": null,
  "lastyear": "1600",
  "lastyearend": null,
  "country": "Nederland",
  "countrycode": "NL",
  "author": "Will Brouwers",
  "created_on": "2019-06-13 18:09:52",
  "modified_on": "2025-06-27 22:22:47",
  "deleted_on": null,
  "feet": "feet",
  "body": "<h1 id=\"h-history\">Historie</h1>\n<div><p>In 2007 werd bij baggerwerkzaamheden in de vaargeul Amsterdam &ndash; Lemmer het wrak van een waterschip uit het einde van de 16e eeuw ontdekt.</p> <p>Het schip is 20 meter lang en bestaat uit een bijna complete romp met voor- en achtersteven. Archeologen onderzochten het schip eerst onder water. Daarna, in 2009, werd een gedeelte gelicht en op land onderzocht. Het schip werd weer afgezonken in het Buiten Ij. Het wrak is voor de toekomst behouden en bovendien kan de locatie gebruikt worden als oefenobject voor onderwaterarcheologen .</p> <p><strong>Waterschip</strong><br>Waterschepen waren vissersschepen die verse vis vervoerden die levend werd gehouden in een waterbak in het ruim (de bun). Deze vissersschepen kwamen van de zestiende tot en met de achttiende eeuw veel voor in de wateren rond Amsterdam. Ze werden ook gebruikt om grote zeeschepen over Pampus te slepen. Dit schip was wellicht op weg naar de vismarkt van Amsterdam om verse vis af te leveren. In het ruim trof men een ruime hoeveelheid visgraten aan. Aan de jaarringen van het hout is afgeleid dat het schip rond 1585 moet zijn gemaakt. Er werd ook een muntje uit 1596 gevonden. Het schip is om nog onbekende redenen rond 1600 gezonken.</p></div>\n<h1 id=\"h-description\">Beschrijving</h1>\n<div><figure class=\"img-wrapper\"><img src=\"/photos/l/00003162.jpg\" alt=\"Een deel van een scheepswrak dat uit het water wordt gehesen.\"> <div class=\"img-source\">Archeologisch Diensten Centrum, Periplus Archeomare, Bureau Monumenten &amp; Archeologie</div> <figcaption class=\"img-description\">.</figcaption> </figure><table class=\"metavalues\"><tbody><tr><th scope=\"row\">Lengte</th><td>65 &frac12; voet (20 m)</td></tr></tbody></table></div>\n<h1 id=\"h-references\">Referenties</h1>\n<div><ul><li>Waldus, W.B. (red. (2010).<br /><a href=\"https://archisarchief.cultureelerfgoed.nl/Archis2/Archeorapporten/17/AR21923/rapport%202064%20VAL%207.pdf\">Wrak VAL7, Buiten IJ.</a><br />ADC Rapport 2064.</li></ul></div>\n",
  "license": {
    "title": "Creative Commons Attribution-ShareAlike 4.0 International License (CC BY-SA 4.0)",
    "href": "https://creativecommons.org/licenses/by-sa/4.0/"
  }
}