{
  "id": "801",
  "code": "colombia",
  "name": "Hr.Ms. Colombia",
  "type": "wreck",
  "lat": "-33.0307719",
  "lon": "28.1788329",
  "location": "East London SA, Verenigd Koninkrijk",
  "firstdate": null,
  "firstyear": "1930",
  "firstyearend": null,
  "lastdate": "1943-02-27",
  "lastyear": "1943",
  "lastyearend": null,
  "country": "Nederland",
  "countrycode": "NL",
  "author": "Will Brouwers",
  "created_on": "2019-07-08 18:32:44",
  "modified_on": "2025-06-07 16:45:56",
  "deleted_on": null,
  "feet": "feet",
  "body": "<h1 id=\"h-history\">Historie</h1>\n<div><p>Het schip was oorspronkelijk het vlaggenschip van de Koninklijke Nederlandse Stoomboot-Maatschappij. Bij de Nederlandse marine moest dit schip de rol van onderzeebootmoederschip vervullen.</p> <p>Toen de Colombia zonk was ze ter hoogte van de Oost kaap en werd ge&euml;scorteerd door de HMS Genista en vliegtuigen van de RAF. Om 11 uur in de ochtend werd ze onder vuur genomen door de Duitse U-516. Drie torpedo's worden afgevuurd. E&eacute;n torpedo raakt de Colombia net voor de brug. De meeste opvarenden werden gered (377), 8 opvarenden raakten vermist.</p></div>\n<h1 id=\"h-description\">Beschrijving</h1>\n<div><p>Tewaterlating 1930<br>In dienst gesteld 20 mei 1941<br>Uit dienst gesteld 27 februari 1943</p> <p>Lengte: 139,3 m<br>Breedte: 18,7 m<br>Holte: 8,1 m</p> <p>Waterverplaatsing: 14.600 ton<br>Bemanning: 273</p> <p>Machinevermogen: 2 x 8.000 pk]<br>Snelheid: 15,5 knopen<br>Bewapening: 4 x 7,6 cm kanon, 8 x 20 mm mitrailleur<br>6 x 12,7 mm mitrailleur, 4 x 7,9 mm mitrailleur</p><table class=\"metavalues\"><tbody></tbody></table></div>\n<h1 id=\"h-references\">Referenties</h1>\n<div><ul><li><a href=\"http://www.dutchsubmarines.com/\">Dutch submarines.</a></li><li><a href=\"https://www.wrecksite.eu/wreck.aspx?17740\">wrakkensite .</a></li><li><a href=\"https://www.maritiemdigitaal.nl/\">Maritiem digitaal.</a></li></ul></div>\n",
  "license": {
    "title": "Creative Commons Attribution-ShareAlike 4.0 International License (CC BY-SA 4.0)",
    "href": "https://creativecommons.org/licenses/by-sa/4.0/"
  }
}